lawrence/__init__.py
lawrence-1.0.0.dist-info/DESCRIPTION.rst
lawrence-1.0.0.dist-info/METADATA
lawrence-1.0.0.dist-info/RECORD
lawrence-1.0.0.dist-info/WHEEL
lawrence-1.0.0.dist-info/entry_points.txt
lawrence-1.0.0.dist-info/metadata.json
lawrence-1.0.0.dist-info/top_level.txt
