Metadata-Version: 2.0
Name: lawrence
Version: 1.0.0
Summary: Website Mockup Utility
Home-page: http://jmroper.com/
Author: John Roper
Author-email: john@jmroper.com
License: GPL3.0
Platform: UNKNOWN
Requires-Python: >=3
Requires-Dist: click
Requires-Dist: Jinja2
